LICENSE
MANIFEST.in
README.rst
setup.py
djangocms_site_search.egg-info/PKG-INFO
djangocms_site_search.egg-info/SOURCES.txt
djangocms_site_search.egg-info/dependency_links.txt
djangocms_site_search.egg-info/requires.txt
djangocms_site_search.egg-info/top_level.txt
site_search/__init__.py
site_search/conf.py
site_search/forms.py
site_search/helpers.py
site_search/models.py
site_search/receivers.py
site_search/urls.py
site_search/utils.py
site_search/views.py
site_search/indexers/__init__.py
site_search/indexers/cms_title.py
site_search/migrations/0001_initial.py
site_search/migrations/__init__.py
site_search/templates/site_search/search_results.html
site_search/templates/site_search/includes/paginator.html
site_search/templates/site_search/includes/search_items.html
site_search/tests/__init__.py
site_search/tests/test_index_management.py
site_search/tests/test_index_search_text.py
site_search/tests/test_model.py
site_search/tests/test_permissions.py
site_search/tests/test_search_fields.py
site_search/tests/test_urls.py
site_search/tests/test_utils.py
site_search/tests/test_view.py
site_search/tests/migrations/0001_initial.py
site_search/tests/migrations/__init__.py