Metadata-Version: 1.1
Name: djangocms-site-search
Version: 0.2.3
Summary: Django model based search for Django CMS
Home-page: https://github.com/AccentDesign/djangocms-site-search
Author: Stuart George
Author-email: stuart@accentdesign.com
License: MIT
Download-URL: https://pypi.python.org/pypi/djangocms-site-search
Keywords: djangocms,django,cms,search,site
Platform: UNKNOWN
Classifier: Development Status :: 5 - Production/Stable
Classifier: Environment :: Web Environment
Classifier: Framework :: Django
Classifier: Framework :: Django :: 1.8
Classifier: Framework :: Django :: 1.9
Classifier: Intended Audience :: Developers
Classifier: License :: OSI Approved :: MIT License
Classifier: Operating System :: OS Independent
Classifier: Programming Language :: Python
Classifier: Programming Language :: Python :: 2.7
Classifier: Programming Language :: Python :: 3.3
Classifier: Programming Language :: Python :: 3.4
Classifier: Topic :: Internet :: WWW/HTTP
